hs_formation/__init__.py
hs_formation/__version__.py
hs_formation/for_aio_http.py
hs_formation/for_requests.py
hs_formation/formation.py
hs_formation/middleware/__init__.py
hs_formation/middleware/accept.py
hs_formation/middleware/breaker.py
hs_formation/middleware/context.py
hs_formation/middleware/context_logger.py
hs_formation/middleware/iobreaker.py
hs_formation/middleware/logger.py
hs_formation/middleware/request_duration.py
hs_formation/middleware/request_id.py
hs_formation/middleware/retry.py
hs_formation/middleware/timeout.py
hs_formation/middleware/ua.py
hs_formation/utils/__init__.py
hs_formation/utils/attrs_serde.py
hs_formation-5.5.0.dist-info/LICENSE.txt
hs_formation-5.5.0.dist-info/METADATA
hs_formation-5.5.0.dist-info/WHEEL
hs_formation-5.5.0.dist-info/RECORD
