Metadata-Version: 2.1
Name: hs-formation
Version: 5.5.0
Summary: A generic functional middleware infrastructure for Python.
Home-page: https://github.com/HiredScorelabs/hs-formation
License: MIT
Keywords: flask,django,requests,middleware,functional
Author: Dotan Nahum
Author-email: jondotan@gmail.com
Requires-Python: >=3.7
Classifier: License :: OSI Approved :: MIT License
Classifier: Programming Language :: Python :: 3
Classifier: Programming Language :: Python :: 3.7
Classifier: Programming Language :: Python :: 3.8
Classifier: Programming Language :: Python :: 3.9
Classifier: Programming Language :: Python :: 3.10
Classifier: Programming Language :: Python :: 3.11
Provides-Extra: lint
Requires-Dist: aiobreaker (>=1.1.0)
Requires-Dist: aiohttp (>=3.7.3)
Requires-Dist: attrs (>=19.1)
Requires-Dist: cytoolz (>=0.9.0)
Requires-Dist: lxml (>=4.2)
Requires-Dist: pybreaker (>=0.4.5)
Requires-Dist: requests (>=2.20)
Requires-Dist: toolz (>=0.9.0)
Requires-Dist: xmltodict (>=0.11.0)
Project-URL: Documentation, https://github.com/jondot/formation
Project-URL: Repository, https://github.com/HiredScorelabs/hs-formation
